{
"meta":{"test_sets":[],"test_metrics":[],"learn_metrics":[{"best_value":"Min","name":"RMSE"}],"launch_mode":"Train","parameters":"","iteration_count":100,"learn_sets":["learn"],"name":"experiment"},
"iterations":[
{"learn":[14.005006],"iteration":0,"passed_time":0.001401813204,"remaining_time":0.1387795072},
{"learn":[13.14441192],"iteration":1,"passed_time":0.002425890365,"remaining_time":0.1188686279},
{"learn":[12.34258257],"iteration":2,"passed_time":0.003676671534,"remaining_time":0.1188790463},
{"learn":[11.64527793],"iteration":3,"passed_time":0.00444150804,"remaining_time":0.106596193},
{"learn":[11.02766183],"iteration":4,"passed_time":0.005357058801,"remaining_time":0.1017841172},
{"learn":[10.43485794],"iteration":5,"passed_time":0.006230806373,"remaining_time":0.09761596651},
{"learn":[9.890641275],"iteration":6,"passed_time":0.007124856682,"remaining_time":0.09465881021},
{"learn":[9.492161212],"iteration":7,"passed_time":0.00814628393,"remaining_time":0.09368226519},
{"learn":[9.105082953],"iteration":8,"passed_time":0.009494761175,"remaining_time":0.09600258521},
{"learn":[8.674157135],"iteration":9,"passed_time":0.0112421666,"remaining_time":0.1011794994},
{"learn":[8.341743544],"iteration":10,"passed_time":0.0121864589,"remaining_time":0.09859953114},
{"learn":[8.049372916],"iteration":11,"passed_time":0.0130819575,"remaining_time":0.09593435499},
{"learn":[7.757318612],"iteration":12,"passed_time":0.01395884568,"remaining_time":0.09341689035},
{"learn":[7.522206899],"iteration":13,"passed_time":0.01485531067,"remaining_time":0.09125405127},
{"learn":[7.297756655],"iteration":14,"passed_time":0.01561448128,"remaining_time":0.0884820606},
{"learn":[7.088359431],"iteration":15,"passed_time":0.01640827369,"remaining_time":0.08614343688},
{"learn":[6.882113791],"iteration":16,"passed_time":0.0172443104,"remaining_time":0.0841928096},
{"learn":[6.704728832],"iteration":17,"passed_time":0.01792414347,"remaining_time":0.08165443135},
{"learn":[6.563881962],"iteration":18,"passed_time":0.0185679717,"remaining_time":0.07915819515},
{"learn":[6.418790279],"iteration":19,"passed_time":0.01941927625,"remaining_time":0.07767710498},
{"learn":[6.315756953],"iteration":20,"passed_time":0.02017044915,"remaining_time":0.07587930873},
{"learn":[6.210157751],"iteration":21,"passed_time":0.02105355723,"remaining_time":0.07464443019},
{"learn":[6.115058449],"iteration":22,"passed_time":0.02200573305,"remaining_time":0.07367136717},
{"learn":[6.014819884],"iteration":23,"passed_time":0.02270596673,"remaining_time":0.07190222799},
{"learn":[5.93117229],"iteration":24,"passed_time":0.02394059589,"remaining_time":0.07182178768},
{"learn":[5.844857622],"iteration":25,"passed_time":0.02495993114,"remaining_time":0.071039804},
{"learn":[5.771145213],"iteration":26,"passed_time":0.02586944993,"remaining_time":0.0699433276},
{"learn":[5.704018229],"iteration":27,"passed_time":0.02688473364,"remaining_time":0.06913217221},
{"learn":[5.665806474],"iteration":28,"passed_time":0.02772110835,"remaining_time":0.06786892045},
{"learn":[5.616500369],"iteration":29,"passed_time":0.02852531836,"remaining_time":0.06655907618},
{"learn":[5.558023666],"iteration":30,"passed_time":0.02931106576,"remaining_time":0.06524075928},
{"learn":[5.510080976],"iteration":31,"passed_time":0.03012858276,"remaining_time":0.06402323837},
{"learn":[5.468747792],"iteration":32,"passed_time":0.03106587509,"remaining_time":0.06307314033},
{"learn":[5.429275534],"iteration":33,"passed_time":0.03186872751,"remaining_time":0.06186282399},
{"learn":[5.402117324],"iteration":34,"passed_time":0.03267496264,"remaining_time":0.06068207348},
{"learn":[5.367635151],"iteration":35,"passed_time":0.03350880588,"remaining_time":0.05957121045},
{"learn":[5.345181232],"iteration":36,"passed_time":0.03459011818,"remaining_time":0.0588966877},
{"learn":[5.319151269],"iteration":37,"passed_time":0.03556967926,"remaining_time":0.05803473985},
{"learn":[5.296134146],"iteration":38,"passed_time":0.03647738404,"remaining_time":0.0570543699},
{"learn":[5.269629003],"iteration":39,"passed_time":0.03731121161,"remaining_time":0.05596681742},
{"learn":[5.251147059],"iteration":40,"passed_time":0.03819382279,"remaining_time":0.05496184255},
{"learn":[5.248003302],"iteration":41,"passed_time":0.03858891508,"remaining_time":0.05328945416},
{"learn":[5.232376509],"iteration":42,"passed_time":0.03988916533,"remaining_time":0.05287633544},
{"learn":[5.213524255],"iteration":43,"passed_time":0.04097529622,"remaining_time":0.05215037701},
{"learn":[5.189691584],"iteration":44,"passed_time":0.04189971026,"remaining_time":0.05121075698},
{"learn":[5.166052198],"iteration":45,"passed_time":0.04287413367,"remaining_time":0.05033050475},
{"learn":[5.140406659],"iteration":46,"passed_time":0.04378277548,"remaining_time":0.04937206596},
{"learn":[5.118929684],"iteration":47,"passed_time":0.044542104,"remaining_time":0.048253946},
{"learn":[5.108792602],"iteration":48,"passed_time":0.04540683168,"remaining_time":0.04726017175},
{"learn":[5.098141225],"iteration":49,"passed_time":0.04620578852,"remaining_time":0.04620578852},
{"learn":[5.085926393],"iteration":50,"passed_time":0.04706726923,"remaining_time":0.04522149397},
{"learn":[5.067816804],"iteration":51,"passed_time":0.04790601556,"remaining_time":0.04422093744},
{"learn":[5.049834901],"iteration":52,"passed_time":0.04908953779,"remaining_time":0.04353223163},
{"learn":[5.03838627],"iteration":53,"passed_time":0.05004949304,"remaining_time":0.04263475333},
{"learn":[5.033534248],"iteration":54,"passed_time":0.05057462719,"remaining_time":0.04137924043},
{"learn":[5.023726885],"iteration":55,"passed_time":0.05130453293,"remaining_time":0.04031070445},
{"learn":[5.01290392],"iteration":56,"passed_time":0.05209208979,"remaining_time":0.03929754142},
{"learn":[5.005569127],"iteration":57,"passed_time":0.05307443228,"remaining_time":0.03843320958},
{"learn":[4.989969032],"iteration":58,"passed_time":0.05420979342,"remaining_time":0.03767121238},
{"learn":[4.976762446],"iteration":59,"passed_time":0.05505983663,"remaining_time":0.03670655775},
{"learn":[4.967222715],"iteration":60,"passed_time":0.05589098297,"remaining_time":0.03573357927},
{"learn":[4.954407599],"iteration":61,"passed_time":0.05680132199,"remaining_time":0.03481371348},
{"learn":[4.942125056],"iteration":62,"passed_time":0.05778195845,"remaining_time":0.03393543591},
{"learn":[4.930230716],"iteration":63,"passed_time":0.05904138723,"remaining_time":0.03321078032},
{"learn":[4.921695642],"iteration":64,"passed_time":0.05999901655,"remaining_time":0.03230716276},
{"learn":[4.906405625],"iteration":65,"passed_time":0.06086751585,"remaining_time":0.03135599301},
{"learn":[4.894330248],"iteration":66,"passed_time":0.0617479652,"remaining_time":0.03041317689},
{"learn":[4.88211557],"iteration":67,"passed_time":0.06263805662,"remaining_time":0.02947673253},
{"learn":[4.877946398],"iteration":68,"passed_time":0.06353101036,"remaining_time":0.0285429177},
{"learn":[4.863182126],"iteration":69,"passed_time":0.06433033294,"remaining_time":0.02757014269},
{"learn":[4.84646533],"iteration":70,"passed_time":0.06518157941,"remaining_time":0.02662346201},
{"learn":[4.838014752],"iteration":71,"passed_time":0.06624156254,"remaining_time":0.02576060766},
{"learn":[4.82981137],"iteration":72,"passed_time":0.06718983821,"remaining_time":0.02485103605},
{"learn":[4.817094767],"iteration":73,"passed_time":0.06831415532,"remaining_time":0.02400227079},
{"learn":[4.808314151],"iteration":74,"passed_time":0.06937718641,"remaining_time":0.0231257288},
{"learn":[4.796235023],"iteration":75,"passed_time":0.07038446621,"remaining_time":0.02222667354},
{"learn":[4.784434534],"iteration":76,"passed_time":0.07130810766,"remaining_time":0.02129982437},
{"learn":[4.774402487],"iteration":77,"passed_time":0.0723388579,"remaining_time":0.02040326761},
{"learn":[4.76731896],"iteration":78,"passed_time":0.07311246143,"remaining_time":0.0194349581},
{"learn":[4.75934113],"iteration":79,"passed_time":0.07394703061,"remaining_time":0.01848675765},
{"learn":[4.754106378],"iteration":80,"passed_time":0.07474898287,"remaining_time":0.01753371203},
{"learn":[4.744002932],"iteration":81,"passed_time":0.07561632458,"remaining_time":0.0165987054},
{"learn":[4.731700554],"iteration":82,"passed_time":0.07633946948,"remaining_time":0.01563579495},
{"learn":[4.723284153],"iteration":83,"passed_time":0.07708953766,"remaining_time":0.01468372146},
{"learn":[4.712232782],"iteration":84,"passed_time":0.07797264346,"remaining_time":0.01375987826},
{"learn":[4.703046867],"iteration":85,"passed_time":0.07892023951,"remaining_time":0.01284748085},
{"learn":[4.698601855],"iteration":86,"passed_time":0.07996891108,"remaining_time":0.01194937752},
{"learn":[4.692429407],"iteration":87,"passed_time":0.08080859999,"remaining_time":0.01101935454},
{"learn":[4.675027364],"iteration":88,"passed_time":0.08163562301,"remaining_time":0.0100897961},
{"learn":[4.662368584],"iteration":89,"passed_time":0.08257706018,"remaining_time":0.009175228909},
{"learn":[4.646206172],"iteration":90,"passed_time":0.0836641219,"remaining_time":0.008274473594},
{"learn":[4.641245848],"iteration":91,"passed_time":0.08569296011,"remaining_time":0.007451561748},
{"learn":[4.633900435],"iteration":92,"passed_time":0.08771849685,"remaining_time":0.006602467505},
{"learn":[4.624738236],"iteration":93,"passed_time":0.08878351586,"remaining_time":0.005667032927},
{"learn":[4.612798287],"iteration":94,"passed_time":0.08977030761,"remaining_time":0.004724753032},
{"learn":[4.605222001],"iteration":95,"passed_time":0.09058948725,"remaining_time":0.003774561969},
{"learn":[4.601725912],"iteration":96,"passed_time":0.09156222682,"remaining_time":0.002831821448},
{"learn":[4.59722371],"iteration":97,"passed_time":0.09263245463,"remaining_time":0.001890458258},
{"learn":[4.580235665],"iteration":98,"passed_time":0.09363748452,"remaining_time":0.000945833177},
{"learn":[4.57591791],"iteration":99,"passed_time":0.09463536336,"remaining_time":0}
]}